apetech_mcp_demo/__init__.py
apetech_mcp_demo-0.1.0.dist-info/WHEEL
apetech_mcp_demo-0.1.0.dist-info/entry_points.txt
apetech_mcp_demo-0.1.0.dist-info/METADATA
apetech_mcp_demo-0.1.0.dist-info/RECORD
