Metadata-Version: 2.3
Name: apetech-mcp-demo
Version: 0.1.0
Summary: Add your description here
Author: lejun.wang
Author-email: lejun.wang <jaime.w@ongineer.cn>
Requires-Dist: mcp[cli]>=1.13.1
Requires-Python: >=3.13
